{
    "isin": "INF789F01UG3",
    "scheme_name": "UTI Large & Mid Cap Fund - Direct Plan - Growth Option",
    "holdings": [
        {
            "name": "HDFC Bank Ltd",
            "weight": 4.73,
            "sector": "Financial Services"
        },
        {
            "name": "Net Current Assets",
            "weight": 4.25,
            "sector": "Other"
        },
        {
            "name": "ICICI Bank Ltd",
            "weight": 3.44,
            "sector": "Financial Services"
        },
        {
            "name": "Infosys Ltd",
            "weight": 3.07,
            "sector": "Technology"
        },
        {
            "name": "Vedanta Ltd",
            "weight": 2.77,
            "sector": "Basic Materials"
        },
        {
            "name": "Power Grid Corp Of India Ltd",
            "weight": 2.75,
            "sector": "Utilities"
        },
        {
            "name": "Larsen & Toubro Ltd",
            "weight": 2.72,
            "sector": "Industrials"
        },
        {
            "name": "Reliance Industries Ltd",
            "weight": 2.45,
            "sector": "Energy"
        },
        {
            "name": "Aurobindo Pharma Ltd",
            "weight": 2.3,
            "sector": "Healthcare"
        },
        {
            "name": "Wipro Ltd",
            "weight": 2.29,
            "sector": "Technology"
        },
        {
            "name": "ITC Ltd",
            "weight": 2.18,
            "sector": "Consumer Defensive"
        },
        {
            "name": "The Federal Bank Ltd",
            "weight": 2.16,
            "sector": "Financial Services"
        },
        {
            "name": "Indus Towers Ltd Ordinary Shares",
            "weight": 2.07,
            "sector": "Communication Services"
        },
        {
            "name": "HCL Technologies Ltd",
            "weight": 1.88,
            "sector": "Technology"
        },
        {
            "name": "Aditya Birla Capital Ltd",
            "weight": 1.84,
            "sector": "Financial Services"
        },
        {
            "name": "State Bank of India",
            "weight": 1.81,
            "sector": "Financial Services"
        },
        {
            "name": "Hero MotoCorp Ltd",
            "weight": 1.74,
            "sector": "Consumer Cyclical"
        },
        {
            "name": "Sundaram Finance Ltd",
            "weight": 1.72,
            "sector": "Financial Services"
        },
        {
            "name": "Tube Investments of India Ltd Ordinary Shares",
            "weight": 1.6,
            "sector": "Industrials"
        },
        {
            "name": "Max Financial Services Ltd",
            "weight": 1.56,
            "sector": "Financial Services"
        },
        {
            "name": "Shriram Finance Ltd",
            "weight": 1.55,
            "sector": "Financial Services"
        },
        {
            "name": "Grasim Industries Ltd",
            "weight": 1.52,
            "sector": "Basic Materials"
        },
        {
            "name": "Phoenix Mills Ltd",
            "weight": 1.51,
            "sector": "Real Estate"
        },
        {
            "name": "Glenmark Pharmaceuticals Ltd",
            "weight": 1.49,
            "sector": "Healthcare"
        },
        {
            "name": "Maruti Suzuki India Ltd",
            "weight": 1.48,
            "sector": "Consumer Cyclical"
        },
        {
            "name": "Mahindra & Mahindra Ltd",
            "weight": 1.45,
            "sector": "Consumer Cyclical"
        },
        {
            "name": "Info Edge (India) Ltd",
            "weight": 1.35,
            "sector": "Communication Services"
        },
        {
            "name": "InterGlobe Aviation Ltd",
            "weight": 1.34,
            "sector": "Industrials"
        },
        {
            "name": "Bank of Maharashtra",
            "weight": 1.28,
            "sector": "Financial Services"
        },
        {
            "name": "Ajanta Pharma Ltd",
            "weight": 1.28,
            "sector": "Healthcare"
        },
        {
            "name": "Bharti Airtel Ltd",
            "weight": 1.27,
            "sector": "Communication Services"
        },
        {
            "name": "Petronet LNG Ltd",
            "weight": 1.27,
            "sector": "Energy"
        },
        {
            "name": "Oberoi Realty Ltd",
            "weight": 1.25,
            "sector": "Real Estate"
        },
        {
            "name": "Mphasis Ltd",
            "weight": 1.24,
            "sector": "Technology"
        },
        {
            "name": "Oil India Ltd",
            "weight": 1.23,
            "sector": "Energy"
        },
        {
            "name": "Life Insurance Corporation of India",
            "weight": 1.22,
            "sector": "Financial Services"
        },
        {
            "name": "ICICI Prudential Life Insurance Co Ltd",
            "weight": 1.15,
            "sector": "Financial Services"
        },
        {
            "name": "Biocon Ltd",
            "weight": 1.12,
            "sector": "Healthcare"
        },
        {
            "name": "Nippon Life India Asset Management Ltd Ordinary Shares",
            "weight": 1.12,
            "sector": "Financial Services"
        },
        {
            "name": "REC Ltd",
            "weight": 1.11,
            "sector": "Financial Services"
        },
        {
            "name": "Coal India Ltd",
            "weight": 1.09,
            "sector": "Energy"
        },
        {
            "name": "Emami Ltd",
            "weight": 1.08,
            "sector": "Consumer Defensive"
        },
        {
            "name": "Crompton Greaves Consumer Electricals Ltd",
            "weight": 1.07,
            "sector": "Consumer Cyclical"
        },
        {
            "name": "NIIT Learning Systems Ltd",
            "weight": 1.07,
            "sector": "Consumer Defensive"
        },
        {
            "name": "G R Infraprojects Ltd",
            "weight": 1.01,
            "sector": "Industrials"
        },
        {
            "name": "Embassy Office Parks REIT",
            "weight": 1.01,
            "sector": "Real Estate"
        },
        {
            "name": "Jubilant Foodworks Ltd",
            "weight": 0.99,
            "sector": "Consumer Cyclical"
        },
        {
            "name": "Oracle Financial Services Software Ltd",
            "weight": 0.98,
            "sector": "Technology"
        },
        {
            "name": "Motilal Oswal Financial Services Ltd",
            "weight": 0.96,
            "sector": "Financial Services"
        },
        {
            "name": "Colgate-Palmolive (India) Ltd",
            "weight": 0.93,
            "sector": "Consumer Defensive"
        },
        {
            "name": "JK Paper Ltd",
            "weight": 0.92,
            "sector": "Basic Materials"
        },
        {
            "name": "Caplin Point Laboratories Ltd",
            "weight": 0.92,
            "sector": "Healthcare"
        },
        {
            "name": "IndusInd Bank Ltd",
            "weight": 0.91,
            "sector": "Financial Services"
        },
        {
            "name": "UPL Ltd",
            "weight": 0.91,
            "sector": "Basic Materials"
        },
        {
            "name": "Great Eastern Shipping Co Ltd",
            "weight": 0.88,
            "sector": "Industrials"
        },
        {
            "name": "Hindustan Petroleum Corp Ltd",
            "weight": 0.83,
            "sector": "Energy"
        },
        {
            "name": "Indian Bank",
            "weight": 0.82,
            "sector": "Financial Services"
        },
        {
            "name": "GHCL Ltd",
            "weight": 0.76,
            "sector": "Basic Materials"
        },
        {
            "name": "General Insurance Corp of India",
            "weight": 0.69,
            "sector": "Financial Services"
        },
        {
            "name": "IndiaMART InterMESH Ltd",
            "weight": 0.67,
            "sector": "Communication Services"
        },
        {
            "name": "Marksans Pharma Ltd",
            "weight": 0.65,
            "sector": "Healthcare"
        },
        {
            "name": "Tata Motors Ltd",
            "weight": 0.55,
            "sector": "Consumer Cyclical"
        },
        {
            "name": "Mahindra Holidays & Resorts India Ltd",
            "weight": 0.55,
            "sector": "Consumer Cyclical"
        },
        {
            "name": "Tips Music Ltd",
            "weight": 0.54,
            "sector": "Communication Services"
        },
        {
            "name": "VRL Logistics Ltd",
            "weight": 0.53,
            "sector": "Industrials"
        },
        {
            "name": "DCM Shriram Ltd",
            "weight": 0.51,
            "sector": "Industrials"
        },
        {
            "name": "Raymond Lifestyle Ltd",
            "weight": 0.5,
            "sector": "Consumer Cyclical"
        },
        {
            "name": "Shivalik Bimetal Controls Ltd",
            "weight": 0.46,
            "sector": "Industrials"
        },
        {
            "name": "Bharti Airtel Ltd (Partly Paid Rs.1.25)",
            "weight": 0.42,
            "sector": "Communication Services"
        },
        {
            "name": "Bharat Petroleum Corp Ltd",
            "weight": 0.41,
            "sector": "Energy"
        },
        {
            "name": "Rossari Biotech Ltd Ordinary Shares",
            "weight": 0.33,
            "sector": "Basic Materials"
        },
        {
            "name": "Indo Count Industries Ltd",
            "weight": 0.24,
            "sector": "Consumer Cyclical"
        },
        {
            "name": "Axis Bank Ltd. Std - Margin",
            "weight": 0.12,
            "sector": "Other"
        },
        {
            "name": "Multi Commodity Exchange of India Ltd",
            "weight": 0.09,
            "sector": "Financial Services"
        },
        {
            "name": "Jindal Stainless Ltd",
            "weight": 0.02,
            "sector": "Basic Materials"
        },
        {
            "name": "Clearing Corporation Of India Ltd. Std - Margin",
            "weight": 0.02,
            "sector": "Other"
        },
        {
            "name": "Balkrishna Industries Ltd",
            "weight": 0.0,
            "sector": "Other"
        },
        {
            "name": "Bajaj Auto Ltd",
            "weight": 0.0,
            "sector": "Other"
        }
    ]
}